clirail/__init__.py
clirail/clirail_main.py
clirail/config.py
clirail/data.py
clirail/messages.py
clirail/printing.py
clirail/xdg.py
clirail-1.7.3.data/scripts/clirail
clirail-1.7.3.dist-info/LICENSE
clirail-1.7.3.dist-info/METADATA
clirail-1.7.3.dist-info/WHEEL
clirail-1.7.3.dist-info/top_level.txt
clirail-1.7.3.dist-info/RECORD
