Metadata-Version: 2.1
Name: clirail
Version: 1.7.3
Summary: Command line application for the iRail API
Home-page: https://framagit.org/Midgard/clirail
Author: Midgard
Project-URL: Source, https://framagit.org/Midgard/clirail
Project-URL: Change log, https://framagit.org/Midgard/clirail/-/blob/master/CHANGELOG.md
Project-URL: Bug tracker, https://framagit.org/Midgard/clirail/-/issues
Classifier: Programming Language :: Python :: 3
Classifier: License :: OSI Approved :: GNU General Public License v3 or later (GPLv3+)
Classifier: License :: OSI Approved :: ISC License (ISCL)
Classifier: Operating System :: OS Independent
Classifier: Natural Language :: English
Classifier: Natural Language :: Dutch
Classifier: Environment :: Console
Classifier: Development Status :: 5 - Production/Stable
Classifier: Intended Audience :: End Users/Desktop
Classifier: Topic :: Utilities
Requires-Python: >=3.6
License-File: LICENSE
Requires-Dist: requests
Requires-Dist: python-dateutil
